microsynphylo/__init__.py
microsynphylo/blocktree.py
microsynphylo/fetch_align_worker.py
microsynphylo/microsynphylo.py
microsynphylo/phylo_worker.py
microsynphylo/tree_visualizer.py
microsynphylo-0.0.3.dist-info/licenses/LICENSE
microsynphylo-0.0.3.dist-info/METADATA
microsynphylo-0.0.3.dist-info/WHEEL
microsynphylo-0.0.3.dist-info/entry_points.txt
microsynphylo-0.0.3.dist-info/top_level.txt
microsynphylo-0.0.3.dist-info/RECORD
