Metadata-Version: 2.4
Name: microsynphylo
Version: 0.0.3
Summary: GUI for Phylogenetic Inference of Genes in Microsyntenic Blocks
Author: Jake Leyhr
License-File: LICENSE
Requires-Dist: PyQt5
Requires-Dist: toytree
Requires-Dist: toyplot
Requires-Dist: pandas
Requires-Dist: numpy<1.23.0,>=1.16.5
Requires-Dist: scipy
Requires-Dist: biopython
Dynamic: author
Dynamic: license-file
Dynamic: requires-dist
Dynamic: summary
